{
  "project_info": {
    "project_number": "364329930269",
    "project_id": "nfcampus-01tsc",
    "storage_bucket": "nfcampus-01tsc.firebasestorage.app"
  },
  "client": [
    {
      "client_info": {
        "mobilesdk_app_id": "1:364329930269:android:74a14d16a97ef1ceae40f4",
        "android_client_info": {
          "package_name": "com.example.nfcampus"
        }
      },
      "oauth_client": [],
      "api_key": [
        {
          "current_key": "AIzaSyCJl88HE-X_qn0Sw5bC-hI-FxfLZGjzmbQ"
        }
      ],
      "services": {
        "appinvite_service": {
          "other_platform_oauth_client": []
        }
      }
    },
    {
      "client_info": {
        "mobilesdk_app_id": "1:364329930269:android:0622100c56830673ae40f4",
        "android_client_info": {
          "package_name": "com.example.nfcampussample"
        }
      },
      "oauth_client": [],
      "api_key": [
        {
          "current_key": "AIzaSyCJl88HE-X_qn0Sw5bC-hI-FxfLZGjzmbQ"
        }
      ],
      "services": {
        "appinvite_service": {
          "other_platform_oauth_client": []
        }
      }
    }
  ],
  "configuration_version": "1"
}